SignalBuilder/__init__.py
SignalBuilder/builder.py
SignalBuilder/functions.py
signalbuilder-0.1.dist-info/licenses/LICENSE.txt
signalbuilder-0.1.dist-info/METADATA
signalbuilder-0.1.dist-info/WHEEL
signalbuilder-0.1.dist-info/top_level.txt
signalbuilder-0.1.dist-info/RECORD
