Metadata-Version: 2.4
Name: signalbuilder
Version: 0.1
Summary: Python library for creating piecewise linear signals
Author-email: Yoshika Govender <yoshi.govender@gmail.com>
Classifier: Programming Language :: Python :: 3
Classifier: Operating System :: OS Independent
Classifier: License :: OSI Approved :: MIT License
Requires-Python: >=3.8
License-File: LICENSE.txt
Requires-Dist: numpy
Requires-Dist: scipy
Requires-Dist: matplotlib
Dynamic: license-file
